{
	"Version": 3,
	"Parameters": [
		{
			"Id": "Param27",
			"GroupId": "ParamGroup",
			"Name": "脸黑"
		},
		{
			"Id": "Param28",
			"GroupId": "ParamGroup",
			"Name": "晕晕开关"
		},
		{
			"Id": "Param29",
			"GroupId": "ParamGroup",
			"Name": "晕晕"
		},
		{
			"Id": "Param26",
			"GroupId": "ParamGroup",
			"Name": "微脸红"
		},
		{
			"Id": "Param24",
			"GroupId": "ParamGroup",
			"Name": "醉脸红"
		},
		{
			"Id": "Param25",
			"GroupId": "ParamGroup",
			"Name": "醉脸红"
		},
		{
			"Id": "Param22",
			"GroupId": "ParamGroup",
			"Name": "流汗"
		},
		{
			"Id": "Param23",
			"GroupId": "ParamGroup",
			"Name": "流汗开关"
		},
		{
			"Id": "Param15",
			"GroupId": "ParamGroup",
			"Name": "尴尬"
		},
		{
			"Id": "Param17",
			"GroupId": "ParamGroup",
			"Name": "尴尬开关"
		},
		{
			"Id": "Param16",
			"GroupId": "ParamGroup",
			"Name": "惊讶"
		},
		{
			"Id": "Param13",
			"GroupId": "ParamGroup",
			"Name": "灵光一现"
		},
		{
			"Id": "Param14",
			"GroupId": "ParamGroup",
			"Name": "灵光一现开关"
		},
		{
			"Id": "Param11",
			"GroupId": "ParamGroup",
			"Name": "叹气开关"
		},
		{
			"Id": "Param12",
			"GroupId": "ParamGroup",
			"Name": "叹气"
		},
		{
			"Id": "Param5",
			"GroupId": "ParamGroup",
			"Name": "生气开关"
		},
		{
			"Id": "Param10",
			"GroupId": "ParamGroup",
			"Name": "生气"
		},
		{
			"Id": "Param30",
			"GroupId": "ParamGroup",
			"Name": "抱胸"
		},
		{
			"Id": "Param21",
			"GroupId": "ParamGroup5",
			"Name": "流泪开关"
		},
		{
			"Id": "Param18",
			"GroupId": "ParamGroup5",
			"Name": "流泪1"
		},
		{
			"Id": "Param19",
			"GroupId": "ParamGroup5",
			"Name": "流泪2"
		},
		{
			"Id": "Param20",
			"GroupId": "ParamGroup5",
			"Name": "流泪3"
		},
		{
			"Id": "Param",
			"GroupId": "ParamGroup2",
			"Name": "前发物理"
		},
		{
			"Id": "Param2",
			"GroupId": "ParamGroup2",
			"Name": "前发物理2"
		},
		{
			"Id": "Param3",
			"GroupId": "ParamGroup2",
			"Name": "中发物理"
		},
		{
			"Id": "Param4",
			"GroupId": "ParamGroup2",
			"Name": "后发物理"
		},
		{
			"Id": "Param6",
			"GroupId": "ParamGroup2",
			"Name": "L外套物理1"
		},
		{
			"Id": "Param7",
			"GroupId": "ParamGroup2",
			"Name": "L外套物理2"
		},
		{
			"Id": "Param8",
			"GroupId": "ParamGroup2",
			"Name": "R外套物理1"
		},
		{
			"Id": "Param9",
			"GroupId": "ParamGroup2",
			"Name": "R外套物理2"
		},
		{
			"Id": "ParamAngleX",
			"GroupId": "",
			"Name": "角度 X"
		},
		{
			"Id": "ParamAngleY",
			"GroupId": "",
			"Name": "角度 Y"
		},
		{
			"Id": "ParamAngleZ",
			"GroupId": "",
			"Name": "角度 Z"
		},
		{
			"Id": "ParamEyeLOpen",
			"GroupId": "",
			"Name": "左眼　开闭"
		},
		{
			"Id": "ParamEyeLSmile",
			"GroupId": "",
			"Name": "左眼　微笑"
		},
		{
			"Id": "ParamEyeROpen",
			"GroupId": "",
			"Name": "右眼　开闭"
		},
		{
			"Id": "ParamEyeRSmile",
			"GroupId": "",
			"Name": "右眼　微笑"
		},
		{
			"Id": "ParamEyeBallX",
			"GroupId": "",
			"Name": "眼珠 X"
		},
		{
			"Id": "ParamEyeBallY",
			"GroupId": "",
			"Name": "眼珠 Y"
		},
		{
			"Id": "ParamBrowLX",
			"GroupId": "",
			"Name": "左眉　左右"
		},
		{
			"Id": "ParamBrowLY",
			"GroupId": "",
			"Name": "左眉上下"
		},
		{
			"Id": "ParamBrowLAngle",
			"GroupId": "",
			"Name": "左眉　角度"
		},
		{
			"Id": "ParamBrowLForm",
			"GroupId": "",
			"Name": "左眉　変形"
		},
		{
			"Id": "ParamBrowRX",
			"GroupId": "",
			"Name": "右眉　左右"
		},
		{
			"Id": "ParamBrowRY",
			"GroupId": "",
			"Name": "右眉　上下"
		},
		{
			"Id": "ParamBrowRAngle",
			"GroupId": "",
			"Name": "右眉　角度"
		},
		{
			"Id": "ParamBrowRForm",
			"GroupId": "",
			"Name": "右眉　変形"
		},
		{
			"Id": "ParamMouthForm",
			"GroupId": "",
			"Name": "嘴　变形"
		},
		{
			"Id": "ParamMouthOpenY",
			"GroupId": "",
			"Name": "嘴　张开和闭合"
		},
		{
			"Id": "ParamCheek",
			"GroupId": "",
			"Name": "脸颊泛红"
		},
		{
			"Id": "ParamBodyAngleX",
			"GroupId": "",
			"Name": "身体旋转　X"
		},
		{
			"Id": "ParamBodyAngleY",
			"GroupId": "",
			"Name": "身体旋转　Y"
		},
		{
			"Id": "ParamBodyAngleZ",
			"GroupId": "",
			"Name": "身体旋转　Z"
		},
		{
			"Id": "ParamBreath",
			"GroupId": "",
			"Name": "呼吸"
		},
		{
			"Id": "ParamHairFront",
			"GroupId": "",
			"Name": "摇动 前发"
		},
		{
			"Id": "ParamHairSide",
			"GroupId": "",
			"Name": "摇动 侧发"
		},
		{
			"Id": "ParamHairBack",
			"GroupId": "",
			"Name": "摇动 后发"
		},
		{
			"Id": "Param_Angle_Rotation3",
			"GroupId": "ParamGroup3",
			"Name": "[0]呆毛旋转"
		},
		{
			"Id": "Param_Angle_Rotation4",
			"GroupId": "ParamGroup3",
			"Name": "[1]呆毛旋转"
		},
		{
			"Id": "Param_Angle_Rotation5",
			"GroupId": "ParamGroup3",
			"Name": "[2]呆毛旋转"
		},
		{
			"Id": "Param_Angle_Rotation6",
			"GroupId": "ParamGroup3",
			"Name": "[3]呆毛旋转"
		},
		{
			"Id": "Param_Angle_Rotation7",
			"GroupId": "ParamGroup4",
			"Name": "[0]呆毛旋转R"
		},
		{
			"Id": "Param_Angle_Rotation8",
			"GroupId": "ParamGroup4",
			"Name": "[1]呆毛旋转R"
		},
		{
			"Id": "Param_Angle_Rotation9",
			"GroupId": "ParamGroup4",
			"Name": "[2]呆毛旋转R"
		},
		{
			"Id": "Param_Angle_Rotation10",
			"GroupId": "ParamGroup4",
			"Name": "[3]呆毛旋转R"
		},
		{
			"Id": "Param_Angle_Rotation11",
			"GroupId": "ParamGroup4",
			"Name": "[4]呆毛旋转R"
		}
	],
	"ParameterGroups": [
		{
			"Id": "ParamGroup",
			"GroupId": "",
			"Name": "表情"
		},
		{
			"Id": "ParamGroup5",
			"GroupId": "",
			"Name": "流泪"
		},
		{
			"Id": "ParamGroup2",
			"GroupId": "",
			"Name": "物理"
		},
		{
			"Id": "ParamGroup3",
			"GroupId": "",
			"Name": "呆毛旋转"
		},
		{
			"Id": "ParamGroup4",
			"GroupId": "",
			"Name": "呆毛旋转R"
		}
	],
	"Parts": [
		{
			"Id": "Part",
			"Name": "耳机"
		},
		{
			"Id": "Part2",
			"Name": "装饰元素"
		},
		{
			"Id": "Part3",
			"Name": "右侧发"
		},
		{
			"Id": "Part4",
			"Name": "左侧发"
		},
		{
			"Id": "Part5",
			"Name": "脸"
		},
		{
			"Id": "Part13",
			"Name": "夹克"
		},
		{
			"Id": "Part14",
			"Name": "衬衣带脖子"
		},
		{
			"Id": "Part15",
			"Name": "后发"
		},
		{
			"Id": "ArtMesh12_Skinning",
			"Name": "呆毛R(蒙皮)"
		},
		{
			"Id": "ArtMesh19_Skinning",
			"Name": "呆毛L(蒙皮)"
		},
		{
			"Id": "Part16",
			"Name": "眼泪"
		},
		{
			"Id": "Part8",
			"Name": "鼻子"
		},
		{
			"Id": "Part6",
			"Name": "右眼"
		},
		{
			"Id": "Part7",
			"Name": "左眼"
		},
		{
			"Id": "Part9",
			"Name": "嘴巴"
		},
		{
			"Id": "Part10",
			"Name": "张嘴"
		},
		{
			"Id": "Part11",
			"Name": "脸阴影"
		},
		{
			"Id": "Part12",
			"Name": "脸皮"
		}
	],
	"CombinedParameters": [
		[
			"Param",
			"Param2"
		],
		[
			"ParamAngleX",
			"ParamAngleY"
		],
		[
			"ParamEyeBallX",
			"ParamEyeBallY"
		],
		[
			"ParamBrowLX",
			"ParamBrowLY"
		],
		[
			"ParamBrowRX",
			"ParamBrowRY"
		],
		[
			"ParamMouthForm",
			"ParamMouthOpenY"
		],
		[
			"ParamBodyAngleX",
			"ParamBodyAngleY"
		]
	]
}